{"Id":"d39319cf-8d9f-4378-bfda-835bf0727196","Nummer":"2023Z12801","Titel":"Tijdelijke regels inzake de instelling van een Klimaatfonds (Tijdelijke wet Klimaatfonds) ","Onderwerp":"Motie van het lid Teunissen over in het Belastingplan 2024 een wettelijke basis creëren voor een bijdrage van grote vervuilers aan het Klimaatfonds ","GestartOp":"2023-07-04T00:00:00+02:00","Kabinetsappreciatie":"Ontraden","GewijzigdOp":"2023-07-07T02:31:26.31+02:00","ApiGewijzigdOp":"2023-07-07T00:32:21.0079324Z","ZaakActor":[{"Id":"1d993019-1a3d-4e5a-a606-4a8ed0cec306","ActorNaam":"C. Teunissen","ActorFractie":"PvdD","GewijzigdOp":"2023-07-05T00:54:02.75+02:00","ApiGewijzigdOp":"2023-07-04T22:55:19.2292271Z"}],"Besluit":[{"Id":"fffb2a19-a9db-4a13-9fba-1bdefc7c66f8","StemmingsSoort":"Met handopsteken","BesluitSoort":"Stemmen - verworpen","GewijzigdOp":"2023-07-07T02:31:26.31+02:00","ApiGewijzigdOp":"2023-07-07T00:31:45.7431691Z","Stemming":[{"Id":"ce71d6eb-14bf-4ba1-a4bb-0033a957b648","Soort":"Voor","FractieGrootte":9,"ActorNaam":"SP","ActorFractie":"SP","GewijzigdOp":"2023-07-07T13:42:59.613+02:00","ApiGewijzigdOp":"2023-07-07T11:44:05.4841517Z"},{"Id":"ecfa9b45-84ce-4eb1-8f8b-052e25ff9051","Soort":"Tegen","FractieGrootte":34,"ActorNaam":"VVD","ActorFractie":"VVD","GewijzigdOp":"2023-07-07T13:42:59.613+02:00","ApiGewijzigdOp":"2023-07-07T11:44:05.2341451Z"},{"Id":"8b00262c-6b06-4610-b84d-2072ca7be46f","Soort":"Tegen","FractieGrootte":5,"ActorNaam":"ChristenUnie","ActorFractie":"ChristenUnie","GewijzigdOp":"2023-07-07T13:42:59.607+02:00","ApiGewijzigdOp":"2023-07-07T11:44:04.8278902Z"},{"Id":"65fbdb71-3660-4dc0-bb50-40ef24a7896a","Soort":"Voor","FractieGrootte":1,"ActorNaam":"Omtzigt","ActorFractie":"Omtzigt","GewijzigdOp":"2023-07-07T13:42:59.607+02:00","ApiGewijzigdOp":"2023-07-07T11:44:04.9685173Z"},{"Id":"86f4ceb5-c978-4651-be61-41ea7de85e49","Soort":"Tegen","FractieGrootte":5,"ActorNaam":"FVD","ActorFractie":"FVD","GewijzigdOp":"2023-07-07T13:42:59.607+02:00","ApiGewijzigdOp":"2023-07-07T11:44:05.1247632Z"},{"Id":"505151e0-9b26-4704-a7af-468c7b076c45","Soort":"Voor","FractieGrootte":9,"ActorNaam":"PvdA","ActorFractie":"PvdA","GewijzigdOp":"2023-07-07T13:42:59.607+02:00","ApiGewijzigdOp":"2023-07-07T11:44:04.7653858Z"},{"Id":"efa320df-ad72-4a9a-b0c1-563e1dd883ea","Soort":"Voor","FractieGrootte":1,"ActorNaam":"Fractie Den Haan","ActorFractie":"Fractie Den Haan","GewijzigdOp":"2023-07-07T13:42:59.607+02:00","ApiGewijzigdOp":"2023-07-07T11:44:05.5779063Z"},{"Id":"2bb88fbb-984c-4bc5-b9cf-59c1da26fb7c","Soort":"Tegen","FractieGrootte":3,"ActorNaam":"Groep Van Haga","ActorFractie":"Groep Van Haga","GewijzigdOp":"2023-07-07T13:42:59.607+02:00","ApiGewijzigdOp":"2023-07-07T11:44:05.3903974Z"},{"Id":"c59fed42-b7ca-41b7-b4a8-5b31c8913bdc","Soort":"Voor","FractieGrootte":1,"ActorNaam":"Gündogan","ActorFractie":"Gündogan","GewijzigdOp":"2023-07-07T13:42:59.607+02:00","ApiGewijzigdOp":"2023-07-07T11:44:05.2810168Z"},{"Id":"fd059a12-934a-44a2-944f-6738b6cb172f","Soort":"Tegen","FractieGrootte":3,"ActorNaam":"JA21","ActorFractie":"JA21","GewijzigdOp":"2023-07-07T13:42:59.607+02:00","ApiGewijzigdOp":"2023-07-07T11:44:05.1716407Z"},{"Id":"53f3c340-1500-4116-8652-6784e4368abd","Soort":"Voor","FractieGrootte":6,"ActorNaam":"PvdD","ActorFractie":"PvdD","GewijzigdOp":"2023-07-07T13:42:59.607+02:00","ApiGewijzigdOp":"2023-07-07T11:44:04.8747627Z"},{"Id":"ad43d53f-d896-4fb6-a936-711f4d3bbfec","Soort":"Tegen","FractieGrootte":17,"ActorNaam":"PVV","ActorFractie":"PVV","GewijzigdOp":"2023-07-07T13:42:59.607+02:00","ApiGewijzigdOp":"2023-07-07T11:44:05.5313849Z"},{"Id":"b8af17d9-1444-45b4-93fc-751fa753f22f","Soort":"Tegen","FractieGrootte":1,"ActorNaam":"BBB","ActorFractie":"BBB","GewijzigdOp":"2023-07-07T13:42:59.607+02:00","ApiGewijzigdOp":"2023-07-07T11:44:05.0153857Z"},{"Id":"b158f3d9-e7c5-47ec-8933-91341746ff1f","Soort":"Voor","FractieGrootte":8,"ActorNaam":"GroenLinks","ActorFractie":"GroenLinks","GewijzigdOp":"2023-07-07T13:42:59.607+02:00","ApiGewijzigdOp":"2023-07-07T11:44:04.7185121Z"},{"Id":"fedc9053-449f-43f2-a6cb-97050b7d21e6","Soort":"Tegen","FractieGrootte":14,"ActorNaam":"CDA","ActorFractie":"CDA","GewijzigdOp":"2023-07-07T13:42:59.607+02:00","ApiGewijzigdOp":"2023-07-07T11:44:04.671636Z"},{"Id":"e3bbcd5b-1409-412e-b1bf-a29ad3856e9a","Soort":"Tegen","FractieGrootte":3,"ActorNaam":"SGP","ActorFractie":"SGP","GewijzigdOp":"2023-07-07T13:42:59.613+02:00","ApiGewijzigdOp":"2023-07-07T11:44:05.3278971Z"},{"Id":"1ea6608e-0bbc-456f-ba31-b79382ca36a7","Soort":"Tegen","FractieGrootte":24,"ActorNaam":"D66","ActorFractie":"D66","GewijzigdOp":"2023-07-07T13:42:59.607+02:00","ApiGewijzigdOp":"2023-07-07T11:44:05.0622656Z"},{"Id":"3a72ae89-fcc3-4a61-aad4-c54603f0ce01","Soort":"Voor","FractieGrootte":1,"ActorNaam":"BIJ1","ActorFractie":"BIJ1","GewijzigdOp":"2023-07-07T13:42:59.607+02:00","ApiGewijzigdOp":"2023-07-07T11:44:04.9216437Z"},{"Id":"753f41a3-a89b-4de0-925a-e3f864b8e6c3","Soort":"Voor","FractieGrootte":2,"ActorNaam":"Volt","ActorFractie":"Volt","GewijzigdOp":"2023-07-07T13:42:59.613+02:00","ApiGewijzigdOp":"2023-07-07T11:44:05.4372715Z"},{"Id":"33f2c8c5-9ad4-4098-b95e-ef32484e1245","Soort":"Voor","FractieGrootte":3,"ActorNaam":"DENK","ActorFractie":"DENK","GewijzigdOp":"2023-07-07T13:42:59.607+02:00","ApiGewijzigdOp":"2023-07-07T11:44:05.6872782Z"}],"Stats":{"Voor":41,"Tegen":109,"Anders":0,"PercentVoor":27,"PercentTegen":73}}]}