{"Id":"41d26944-8216-4de4-90f0-e1a9fdd3300a","Nummer":"2023Z10460","Titel":"Voorjaarsnota 2023","Onderwerp":"Motie van het lid Azarkan over de IACK pas laten vervallen als de bijna gratis kinderopvang ingaat ","GewijzigdOp":"2023-06-13T16:06:16.75+02:00","Kabinetsappreciatie":"Ontraden","Indieners":[["F. Azarkan","DENK"]],"Stemmingen":[{"Resultaat":"Verworpen.","Fracties":{"Groep Van Haga":"Voor","Fractie Den Haan":"Voor","VVD":"Tegen","GroenLinks":"Voor","D66":"Tegen","Gündogan":"Voor","DENK":"Voor","JA21":"Voor","CDA":"Tegen","PvdD":"Voor","BBB":"Voor","PvdA":"Voor","SGP":"Tegen","Volt":"Voor","FVD":"Voor","SP":"Voor","PVV":"Voor","Omtzigt":"Tegen","ChristenUnie":"Tegen","BIJ1":"Voor"},"Voor":69,"Tegen":80,"Anders":0,"PercentVoor":46,"PercentTegen":54}]}