{"Id":"3e8c5bba-96e4-4efe-81e1-f7d5ab48c248","Nummer":"2023Z18667","Titel":"Luchtvaartbeleid","Onderwerp":"Motie van het lid Krul over bij de evaluatie van het steunpakket een analyse toevoegen om in de toekomst stevigere en verplichtende voorwaarden toe te voegen","GewijzigdOp":"2023-10-27T10:03:01.993+02:00","Kabinetsappreciatie":"Oordeel Kamer","Indieners":[["H.M. Krul","CDA"]],"Stemmingen":[{"Resultaat":"Aangenomen.","Fracties":{"BIJ1":"Voor","SP":"Voor","Omtzigt":"Voor","CDA":"Voor","PVV":"Voor","DENK":"Voor","BBB":"Tegen","VVD":"Voor","Volt":"Voor","PvdA":"Voor","FVD":"Tegen","Fractie Den Haan":"Tegen","GroenLinks":"Voor","Gündogan":"Niet deelgenomen","PvdD":"Voor","Ephraim":"Niet deelgenomen","Groep Van Haga":"Tegen","ChristenUnie":"Voor","SGP":"Voor","JA21":"Tegen","D66":"Voor"},"Voor":135,"Tegen":13,"Anders":2,"PercentVoor":91,"PercentTegen":9}]}