{"Id":"596e4f16-1524-4a58-b5f8-104153c02c41","Nummer":"2023Z16767","Titel":"Vaststelling van de begrotingsstaat van het Ministerie van Financiën (IXB) en de begrotingsstaat van Nationale Schuld (IXA) voor het jaar 2024","Onderwerp":"Motie van de leden Alkaya en Dassen over het schrappen van de verlaging van de mkb-winstvrijstelling ","GewijzigdOp":"2023-10-10T16:56:58.01+02:00","Kabinetsappreciatie":"Ontraden","Indieners":[["M.Ö. Alkaya","SP"],["L.A.J.M. Dassen","Volt"]],"Stemmingen":[{"Resultaat":"Verworpen.","Fracties":{"BIJ1":"Voor","Groep Van Haga":"Voor","D66":"Tegen","JA21":"Tegen","BBB":"Voor","GroenLinks":"Tegen","ChristenUnie":"Tegen","PvdD":"Voor","SGP":"Voor","Omtzigt":"Niet deelgenomen","DENK":"Voor","CDA":"Tegen","Fractie Den Haan":"Voor","FVD":"Voor","PvdA":"Tegen","SP":"Voor","VVD":"Tegen","Volt":"Voor","Ephraim":"Niet deelgenomen","Gündogan":"Voor","PVV":"Voor"},"Voor":53,"Tegen":94,"Anders":2,"PercentVoor":36,"PercentTegen":64}]}