{"Id":"bc50e7d3-5e70-4a1c-ab6e-5dc16e6b3ee8","Nummer":"2023Z10899","Titel":"Wijziging van de Participatiewet ten behoeve van de werkvoorzieningen voor visueel beperkten","Onderwerp":"Motie van het lid De Kort over een aanspreekpunt waar de mogelijkheden om visueel beperkten in dienst te nemen inzichtelijk worden gemaakt voor werkgevers ","GewijzigdOp":"2023-06-20T15:52:50.03+02:00","Kabinetsappreciatie":"Oordeel Kamer","Indieners":[["A.H.J. de Kort","VVD"]],"Stemmingen":[{"Resultaat":"Aangenomen.","Fracties":{"PvdD":"Voor","Gündogan":"Voor","SP":"Voor","Groep Van Haga":"Voor","GroenLinks":"Voor","PVV":"Voor","VVD":"Voor","JA21":"Voor","ChristenUnie":"Voor","Omtzigt":"Niet deelgenomen","Fractie Den Haan":"Voor","D66":"Voor","SGP":"Voor","PvdA":"Voor","DENK":"Voor","BIJ1":"Voor","FVD":"Voor","Volt":"Voor","BBB":"Voor","CDA":"Voor"},"Voor":148,"Tegen":0,"Anders":1,"PercentVoor":100,"PercentTegen":0}]}