{"Id":"6c7bbc32-3879-40ec-aff5-6e81f2f93564","Nummer":"2023Z17386","Titel":"Vaststelling van de begrotingsstaten van het Ministerie van Sociale Zaken en Werkgelegenheid (XV) voor het jaar 2024","Onderwerp":"Motie van het lid Palland c.s. over bij het verhogen van het minimumloon in Caribisch Nederland ook inzetten op verlaging van de werkgeverslasten ","GewijzigdOp":"2023-10-13T11:11:33.11+02:00","Kabinetsappreciatie":"Oordeel Kamer","Indieners":[["H.M. Palland","CDA"],["A.H.J. de Kort","VVD"],["D.G.M. Ceder","ChristenUnie"]],"Stemmingen":[]}