{"Id":"f17100c4-0fae-49f7-95b0-80d329e1a7d1","Nummer":"2023Z04372","Titel":"Justitiële Inrichtingen","Onderwerp":"Motie van de leden Van Nispen en Hijink over het op korte termijn uitbreiden van de tbs-capaciteit in publieke handen","GewijzigdOp":"2023-03-21T15:43:28.523+01:00","Kabinetsappreciatie":"Ontraden","Indieners":[["M. van Nispen","SP"],["H.P.M. Hijink","SP"]],"Stemmingen":[{"Resultaat":"Verworpen.","Fracties":{"PVV":"Tegen","BBB":"Voor","D66":"Tegen","Groep Van Haga":"Voor","FVD":"Voor","PvdD":"Voor","DENK":"Voor","SGP":"Voor","SP":"Voor","Volt":"Voor","Gündogan":"Voor","Omtzigt":"Voor","GroenLinks":"Voor","BIJ1":"Niet deelgenomen","Fractie Den Haan":"Tegen","CDA":"Tegen","JA21":"Voor","PvdA":"Voor","VVD":"Tegen","ChristenUnie":"Tegen"},"Voor":54,"Tegen":95,"Anders":1,"PercentVoor":36,"PercentTegen":64}]}