{"Id":"cb764ddc-47c6-467f-9a21-0d366014a2f7","Nummer":"2023Z08637","Titel":"Grondstoffenvoorzieningszekerheid","Onderwerp":"Motie van het lid Van der Graaf over een passend en haalbaar percentage recyclaat in kleding verplicht stellen ","GewijzigdOp":"2023-10-26T14:47:24.297+02:00","Kabinetsappreciatie":"Ontraden, tenzij gewijzigd","Indieners":[["S.J.F. van der Graaf","ChristenUnie"]],"Stemmingen":[{"Resultaat":"Verworpen.","Fracties":{"VVD":"Tegen","Groep Van Haga":"Tegen","FVD":"Tegen","Fractie Den Haan":"Voor","CDA":"Tegen","JA21":"Tegen","PvdA":"Voor","GroenLinks":"Voor","PvdD":"Voor","PVV":"Tegen","SGP":"Voor","Volt":"Voor","DENK":"Tegen","ChristenUnie":"Voor","D66":"Voor","BBB":"Tegen","Ephraim":"Niet deelgenomen","Omtzigt":"Tegen","SP":"Voor","Gündogan":"Niet deelgenomen","BIJ1":"Voor"},"Voor":68,"Tegen":80,"Anders":2,"PercentVoor":45,"PercentTegen":55}]}