{"Id":"678d1f59-4c57-444f-a7dc-fb02aa696575","Nummer":"2023Z01126","Titel":"Landbouw- en Visserijraad","Onderwerp":"Motie van de leden Van der Plas en Eppink over met de Deltalanden in gesprek  gaan om binnen de EU te komen tot gedifferentieerd landbouwbeleid","GewijzigdOp":"2023-01-26T19:29:25.503+01:00","Kabinetsappreciatie":"Ontraden","Indieners":[["D.J. Eppink","JA21"],["C.A.M. van der Plas","BBB"]],"Stemmingen":[{"Resultaat":"Verworpen.","Fracties":{"BBB":"Voor","VVD":"Tegen","Volt":"Tegen","Groep Van Haga":"Voor","JA21":"Voor","PvdA":"Tegen","GroenLinks":"Tegen","PVV":"Voor","ChristenUnie":"Tegen","FVD":"Voor","D66":"Tegen","SP":"Tegen","SGP":"Voor","CDA":"Tegen","Omtzigt":"Tegen","BIJ1":"Tegen","Gündogan":"Niet deelgenomen","PvdD":"Tegen","Fractie Den Haan":"Tegen","DENK":"Tegen"},"Voor":32,"Tegen":117,"Anders":1,"PercentVoor":21,"PercentTegen":79}]}