{"Id":"344dd343-72c0-4bef-aca8-ac6a216bbf5e","Nummer":"2023Z07290","Titel":"Landbouw- en Visserijraad","Onderwerp":"Motie van het lid Van der Plas over een gelijkwaardige regeling per schip ontwikkelen die in 2023 nog wordt opengesteld","GewijzigdOp":"2023-04-21T10:07:39.467+02:00","Kabinetsappreciatie":"Ontraden","Indieners":[["C.A.M. van der Plas","BBB"]],"Stemmingen":[{"Resultaat":"Verworpen.","Fracties":{"DENK":"Tegen","CDA":"Tegen","SGP":"Voor","Groep Van Haga":"Voor","D66":"Tegen","Gündogan":"Tegen","VVD":"Tegen","Fractie Den Haan":"Niet deelgenomen","PVV":"Voor","BIJ1":"Niet deelgenomen","ChristenUnie":"Tegen","FVD":"Voor","JA21":"Voor","PvdA":"Tegen","SP":"Tegen","PvdD":"Tegen","Volt":"Tegen","GroenLinks":"Tegen","BBB":"Voor","Omtzigt":"Voor"},"Voor":33,"Tegen":115,"Anders":2,"PercentVoor":22,"PercentTegen":78}]}