{"Id":"0d4070bd-0ee9-4d57-9a96-7fd0e34e7de3","Nummer":"2023Z00959","Titel":"Wijziging van de Wet op het hoger onderwijs en wetenschappelijk onderzoek in verband met het toevoegen van decentrale loting als selectiemethode voor opleidingen met capaciteitsfixus in het hoger onderwijs","Onderwerp":"Motie van de leden El Yassini en Van der Woude over het niet direct of indirect selecteren door opleidingen op persoonlijke kenmerken","GewijzigdOp":"2023-12-07T11:05:51.643+01:00","Kabinetsappreciatie":"Ontraden","Indieners":[["H.H. van der Woude","VVD"],["Z. El Yassini","VVD"]],"Stemmingen":[]}