{"Id":"ee7c4668-d4f4-46ae-9793-34ca81291e8a","Nummer":"2023Z20150","Titel":"Milieuraad","Onderwerp":"Motie van het lid Christine Teunissen c.s. over in de onderhandelingen over de EU-Bodemrichtlijn pleiten voor het handhaven van het ‘one out, all out’ principe","GewijzigdOp":"2023-12-15T10:49:10.527+01:00","Kabinetsappreciatie":"Geen (expliciete) appreciatie","Indieners":[["I. Kostic","PvdD"],["C. (Christine) Teunissen","PvdD"],["L. Bromet","GroenLinks-PvdA"]],"Stemmingen":[{"Resultaat":"Verworpen.","Fracties":{"D66":"Voor","SGP":"Tegen","CDA":"Tegen","NSC":"Tegen","PVV":"Tegen","DENK":"Tegen","FVD":"Tegen","ChristenUnie":"Tegen","VVD":"Tegen","GroenLinks-PvdA":"Voor","PvdD":"Voor","Volt":"Voor","BBB":"Tegen","JA21":"Tegen","SP":"Voor"},"Voor":44,"Tegen":106,"Anders":0,"PercentVoor":29,"PercentTegen":71}]}