{"Id":"bbe7149b-54c7-44fc-94f9-ee3d906bfb36","Nummer":"2023Z04816","Titel":"Europese Raad","Onderwerp":"Motie van het lid Van der Plas c.s. over een bredere versoepeling van staatssteunkaders voor mkb-bedrijven in krimpregio's ","GewijzigdOp":"2023-03-22T15:15:39.307+01:00","Kabinetsappreciatie":"Ontraden","Indieners":[["D.J. Eppink","JA21"],["R. Bisschop","SGP"],["P.H. Omtzigt","Omtzigt"],["C.A.M. van der Plas","BBB"]],"Stemmingen":[{"Resultaat":"Verworpen.","Fracties":{"Omtzigt":"Voor","GroenLinks":"Voor","VVD":"Tegen","JA21":"Voor","Volt":"Tegen","Groep Van Haga":"Voor","PVV":"Voor","SP":"Tegen","CDA":"Tegen","FVD":"Voor","ChristenUnie":"Tegen","D66":"Tegen","BIJ1":"Niet deelgenomen","PvdD":"Tegen","BBB":"Voor","Fractie Den Haan":"Tegen","SGP":"Voor","PvdA":"Voor","DENK":"Tegen","Gündogan":"Tegen"},"Voor":50,"Tegen":99,"Anders":1,"PercentVoor":33,"PercentTegen":67}]}