{"Id":"7600e219-ced9-453a-86aa-7ab522920123","Nummer":"2023Z07917","Titel":"Bestrijding georganiseerde criminaliteit","Onderwerp":"Gewijzigde motie van het lid Leijten over het uitgangspunt in het personeelsbeleid dat wie verantwoordelijk is voor problemen deze niet kan oplossen (t.v.v. 29911-410)","GewijzigdOp":"2023-05-10T08:13:35.32+02:00","Kabinetsappreciatie":"Niet beschikbaar bij gewijzigde moties en/of amendementen","Indieners":[["R.M. Leijten","SP"]],"Stemmingen":[{"Resultaat":"Verworpen.","Fracties":{"PVV":"Tegen","JA21":"Tegen","SGP":"Tegen","D66":"Tegen","VVD":"Tegen","Volt":"Tegen","Omtzigt":"Tegen","ChristenUnie":"Tegen","PvdA":"Tegen","Gündogan":"Niet deelgenomen","BBB":"Voor","GroenLinks":"Tegen","FVD":"Voor","SP":"Voor","Groep Van Haga":"Tegen","DENK":"Voor","PvdD":"Voor","Fractie Den Haan":"Voor","BIJ1":"Voor","CDA":"Tegen"},"Voor":25,"Tegen":123,"Anders":1,"PercentVoor":16,"PercentTegen":84}]}