{"Id":"bfa2f64c-2f3b-48d9-aff7-00589e7c02a2","Nummer":"2023Z06569","Titel":"Wijziging van de Wet donorgegevens kunstmatige bevruchting in verband met de tweede evaluatie van de wet, het actieplan ter ondersteuning van donorkinderen en de omvorming van de Stichting donorgegevens kunstmatige bevruchting tot publiekrechtelijk zelfstandig bestuursorgaan","Onderwerp":"Motie van de leden Paulusma en Romke de Jong over de doelmatigheid en doeltreffendheid van een verlaagd btw-tarief, een btw-nultarief of een btw-vrijstelling voor menselijke geslachtscellen onderzoeken","GewijzigdOp":"2023-09-15T09:48:18.817+02:00","Kabinetsappreciatie":"Verzocht motie aan te houden","Indieners":[["R.H. (Romke) de Jong","D66"],["W. Paulusma","D66"]],"Stemmingen":[]}