{"Id":"66d16eaa-f42f-4819-8c45-57f4dbe85bb2","Nummer":"2023Z10852","Titel":"Indonesië","Onderwerp":"Motie van het lid Van Haga over eerherstel voor generaal Spoor en kapitein Westerling ","GewijzigdOp":"2023-06-20T15:58:10.693+02:00","Kabinetsappreciatie":"Ontraden","Indieners":[["W.R. van Haga","Groep Van Haga"]],"Stemmingen":[{"Resultaat":"Verworpen.","Fracties":{"Groep Van Haga":"Voor","PvdD":"Tegen","BBB":"Tegen","Volt":"Tegen","SP":"Tegen","BIJ1":"Tegen","PvdA":"Tegen","CDA":"Tegen","SGP":"Tegen","VVD":"Tegen","Gündogan":"Tegen","DENK":"Tegen","GroenLinks":"Tegen","ChristenUnie":"Tegen","D66":"Tegen","PVV":"Voor","Omtzigt":"Niet deelgenomen","JA21":"Tegen","Fractie Den Haan":"Tegen","FVD":"Voor"},"Voor":25,"Tegen":123,"Anders":1,"PercentVoor":16,"PercentTegen":84}]}