{"Id":"ca74499c-9bde-4fb5-b8f1-18455a53c138","Nummer":"2021Z22235","Titel":"Infectieziektenbestrijding","Onderwerp":"Motie van het lid Van der Plas c.s. over het kwalificeren van de buitensportsector als essentiële sector","GewijzigdOp":"2023-02-15T15:16:57.383+01:00","Kabinetsappreciatie":"Ontraden","Indieners":[["C.A.M. van der Plas","BBB"],["W.R. van Haga","Groep Van Haga"],["N.J.F. Pouw-Verweij","JA21"],["T. Kuzu","DENK"]],"Stemmingen":[{"Resultaat":"Verworpen.","Fracties":{"Volt":"Voor","FVD":"Voor","D66":"Tegen","BIJ1":"Tegen","JA21":"Voor","PvdD":"Voor","DENK":"Voor","Fractie Den Haan":"Tegen","BBB":"Voor","Omtzigt":"Tegen","SGP":"Tegen","ChristenUnie":"Tegen","PvdA":"Tegen","PVV":"Voor","GroenLinks":"Voor","Groep Van Haga":"Voor","CDA":"Tegen","VVD":"Tegen","SP":"Voor"},"Voor":58,"Tegen":92,"Anders":0,"PercentVoor":38,"PercentTegen":62}]}