{"Id":"811b1ed3-8f96-406c-b49e-985024b7ede6","Nummer":"2023Z11047","Titel":"Infectieziektenbestrijding","Onderwerp":"Motie van de leden Agema en Van der Plas over investeren in robuuste ziekenhuizen die een gezondheidscrisis kunnen opvangen ","GewijzigdOp":"2023-06-20T15:58:20.817+02:00","Kabinetsappreciatie":"Ontraden","Indieners":[["M. Agema","PVV"],["C.A.M. van der Plas","BBB"]],"Stemmingen":[{"Resultaat":"Verworpen.","Fracties":{"DENK":"Voor","CDA":"Tegen","GroenLinks":"Voor","BIJ1":"Voor","FVD":"Voor","Groep Van Haga":"Voor","PvdA":"Voor","PvdD":"Voor","ChristenUnie":"Tegen","Gündogan":"Tegen","D66":"Tegen","Volt":"Voor","Omtzigt":"Niet deelgenomen","Fractie Den Haan":"Voor","VVD":"Tegen","BBB":"Voor","SGP":"Voor","JA21":"Voor","SP":"Voor","PVV":"Voor"},"Voor":71,"Tegen":77,"Anders":1,"PercentVoor":47,"PercentTegen":53}]}