{"Id":"1c93b73f-346f-4880-9152-fc3c37107b02","Nummer":"2022Z13411","Titel":"Infectieziektenbestrijding","Onderwerp":"Motie van het lid Van Houwelingen over in de doodsoorzaakverklaring kunnen opnemen of de overledene een coronavaccinatie heeft gehad ","GestartOp":"2022-06-28T00:00:00+02:00","Kabinetsappreciatie":"Ontraden","GewijzigdOp":"2022-07-05T16:53:23.683+02:00","ApiGewijzigdOp":"2022-07-05T14:53:57.8661247Z","ZaakActor":[{"Id":"681a7558-2f67-44ea-9ab5-3a3badc712ed","ActorNaam":"P. van Houwelingen","ActorFractie":"FVD","GewijzigdOp":"2022-06-28T17:48:23.537+02:00","ApiGewijzigdOp":"2022-06-28T15:49:01.1250089Z"}],"Besluit":[{"Id":"881a7c4a-3c2e-4d8f-9583-69479c37471f","StemmingsSoort":"Met handopsteken","BesluitSoort":"Stemmen - verworpen","GewijzigdOp":"2022-07-05T16:53:23.683+02:00","ApiGewijzigdOp":"2022-07-05T14:53:57.8973943Z","Stemming":[{"Id":"bfdcf9cb-c998-4937-9a13-072649bdc09d","Soort":"Tegen","FractieGrootte":9,"ActorNaam":"PvdA","ActorFractie":"PvdA","GewijzigdOp":"2022-07-06T11:11:25.937+02:00","ApiGewijzigdOp":"2022-07-06T09:12:49.202087Z"},{"Id":"17def6af-d15a-4e5d-a7e9-12b8ae578cc1","Soort":"Tegen","FractieGrootte":24,"ActorNaam":"D66","ActorFractie":"D66","GewijzigdOp":"2022-07-06T11:11:25.937+02:00","ApiGewijzigdOp":"2022-07-06T09:12:49.3583384Z"},{"Id":"89a4a699-3155-4113-b974-1a7e135ca200","Soort":"Voor","FractieGrootte":5,"ActorNaam":"FVD","ActorFractie":"FVD","GewijzigdOp":"2022-07-06T11:11:25.937+02:00","ApiGewijzigdOp":"2022-07-06T09:12:49.155206Z"},{"Id":"90b2f7ef-54d9-4873-b10f-2e4bdb211aaa","Soort":"Tegen","FractieGrootte":6,"ActorNaam":"PvdD","ActorFractie":"PvdD","GewijzigdOp":"2022-07-06T11:11:25.937+02:00","ApiGewijzigdOp":"2022-07-06T09:12:48.7020686Z"},{"Id":"0514b2de-5142-4e86-9374-31a638b9dc2e","Soort":"Tegen","FractieGrootte":5,"ActorNaam":"ChristenUnie","ActorFractie":"ChristenUnie","GewijzigdOp":"2022-07-06T11:11:25.92+02:00","ApiGewijzigdOp":"2022-07-06T09:12:49.3427108Z"},{"Id":"5afada4c-39d4-469d-bacb-39cbd2a3d808","Soort":"Tegen","FractieGrootte":1,"ActorNaam":"Gündogan","ActorFractie":"Gündogan","GewijzigdOp":"2022-07-06T11:11:25.937+02:00","ApiGewijzigdOp":"2022-07-06T09:12:48.7176938Z"},{"Id":"960d8da9-f43a-4b3c-8dff-3fd40ed800b9","Soort":"Tegen","FractieGrootte":2,"ActorNaam":"Volt","ActorFractie":"Volt","GewijzigdOp":"2022-07-06T11:11:25.937+02:00","ApiGewijzigdOp":"2022-07-06T09:12:48.7333196Z"},{"Id":"2f9534c4-0eb1-4669-9c38-5195720aa83b","Soort":"Tegen","FractieGrootte":1,"ActorNaam":"Fractie Den Haan","ActorFractie":"Fractie Den Haan","GewijzigdOp":"2022-07-06T11:11:25.937+02:00","ApiGewijzigdOp":"2022-07-06T09:12:49.3114714Z"},{"Id":"ed1befbe-9027-4c20-98b4-613fc676050f","Soort":"Voor","FractieGrootte":1,"ActorNaam":"BBB","ActorFractie":"BBB","GewijzigdOp":"2022-07-06T11:11:25.92+02:00","ApiGewijzigdOp":"2022-07-06T09:12:48.4989391Z"},{"Id":"590c79da-29d2-45dc-aaf1-72ce9bd9d19c","Soort":"Tegen","FractieGrootte":1,"ActorNaam":"Omtzigt","ActorFractie":"Omtzigt","GewijzigdOp":"2022-07-06T11:11:25.937+02:00","ApiGewijzigdOp":"2022-07-06T09:12:48.467687Z"},{"Id":"cc628d56-9899-4a65-af6e-746565ef15b4","Soort":"Tegen","FractieGrootte":9,"ActorNaam":"SP","ActorFractie":"SP","GewijzigdOp":"2022-07-06T11:11:25.937+02:00","ApiGewijzigdOp":"2022-07-06T09:12:48.9833332Z"},{"Id":"0195ad68-d419-4e8c-97d4-8268b86518e5","Soort":"Tegen","FractieGrootte":34,"ActorNaam":"VVD","ActorFractie":"VVD","GewijzigdOp":"2022-07-06T11:11:25.937+02:00","ApiGewijzigdOp":"2022-07-06T09:12:49.0458284Z"},{"Id":"aedc246c-517c-4acc-8053-8fe369d194c2","Soort":"Tegen","FractieGrootte":1,"ActorNaam":"BIJ1","ActorFractie":"BIJ1","GewijzigdOp":"2022-07-06T11:11:25.92+02:00","ApiGewijzigdOp":"2022-07-06T09:12:48.639568Z"},{"Id":"be3e296d-3aae-4447-987f-9ba4069a11a0","Soort":"Tegen","FractieGrootte":3,"ActorNaam":"Groep Van Haga","ActorFractie":"Groep Van Haga","GewijzigdOp":"2022-07-06T11:11:25.937+02:00","ApiGewijzigdOp":"2022-07-06T09:12:48.7489463Z"},{"Id":"0dd08c6a-0030-4e10-81d9-9ca0dfce33fa","Soort":"Voor","FractieGrootte":17,"ActorNaam":"PVV","ActorFractie":"PVV","GewijzigdOp":"2022-07-06T11:11:25.937+02:00","ApiGewijzigdOp":"2022-07-06T09:12:48.5145644Z"},{"Id":"84fa660e-d700-4360-bbd0-bec54840875a","Soort":"Tegen","FractieGrootte":3,"ActorNaam":"DENK","ActorFractie":"DENK","GewijzigdOp":"2022-07-06T11:11:25.937+02:00","ApiGewijzigdOp":"2022-07-06T09:12:49.295835Z"},{"Id":"bf241f3b-742d-45c8-93c4-d841f9268977","Soort":"Tegen","FractieGrootte":14,"ActorNaam":"CDA","ActorFractie":"CDA","GewijzigdOp":"2022-07-06T11:11:25.92+02:00","ApiGewijzigdOp":"2022-07-06T09:12:49.1864597Z"},{"Id":"2a144154-f12a-47c3-a6a3-e163b40d5cac","Soort":"Tegen","FractieGrootte":8,"ActorNaam":"GroenLinks","ActorFractie":"GroenLinks","GewijzigdOp":"2022-07-06T11:11:25.937+02:00","ApiGewijzigdOp":"2022-07-06T09:12:48.5458132Z"},{"Id":"696c9d4a-29a0-4e1c-8479-f27d9d27d7c5","Soort":"Tegen","FractieGrootte":3,"ActorNaam":"JA21","ActorFractie":"JA21","GewijzigdOp":"2022-07-06T11:11:25.937+02:00","ApiGewijzigdOp":"2022-07-06T09:12:48.623942Z"},{"Id":"ddfffd28-899c-49ff-9970-fc76f16b73f0","Soort":"Voor","FractieGrootte":3,"ActorNaam":"SGP","ActorFractie":"SGP","GewijzigdOp":"2022-07-06T11:11:25.937+02:00","ApiGewijzigdOp":"2022-07-06T09:12:49.2802118Z"}],"Stats":{"Voor":26,"Tegen":124,"Anders":0,"PercentVoor":17,"PercentTegen":83}}]}