{"Id":"afbc0329-b4ae-46cb-957c-e8e7010ba5d1","Nummer":"2022Z25980","Titel":"Luchtvaartbeleid","Onderwerp":"Motie van het lid Van Raan over nog deze week de ZZS-gegevens van Schiphol opeisen","GestartOp":"2022-12-21T00:00:00+01:00","Kabinetsappreciatie":"Ontraden","GewijzigdOp":"2022-12-22T14:43:55.97+01:00","ApiGewijzigdOp":"2022-12-22T14:27:00.6445975Z","ZaakActor":[{"Id":"f9156816-1af4-4826-8bc3-457c31599cfa","ActorNaam":"L. van Raan","ActorFractie":"PvdD","GewijzigdOp":"2022-12-21T17:06:41.547+01:00","ApiGewijzigdOp":"2022-12-21T16:07:37.1718141Z"}],"Besluit":[{"Id":"3d7abde4-6ef9-4fd2-b8e5-b7614463ce53","StemmingsSoort":"Met handopsteken","BesluitSoort":"Stemmen - verworpen","GewijzigdOp":"2022-12-22T14:43:55.967+01:00","ApiGewijzigdOp":"2022-12-22T13:44:15.794126Z","Stemming":[{"Id":"ad458466-9d01-457c-80df-04ff6a423ff6","Soort":"Tegen","FractieGrootte":24,"ActorNaam":"D66","ActorFractie":"D66","GewijzigdOp":"2022-12-23T11:10:17.497+01:00","ApiGewijzigdOp":"2022-12-23T10:10:36.8211044Z"},{"Id":"5fd2a0e8-efad-4715-9a43-09c176889f2f","Soort":"Tegen","FractieGrootte":34,"ActorNaam":"VVD","ActorFractie":"VVD","GewijzigdOp":"2022-12-23T11:10:17.5+01:00","ApiGewijzigdOp":"2022-12-23T10:10:38.0554885Z"},{"Id":"60ae16ec-7949-411e-bd31-17a90194f662","Soort":"Voor","FractieGrootte":2,"ActorNaam":"Volt","ActorFractie":"Volt","GewijzigdOp":"2022-12-23T11:10:17.5+01:00","ApiGewijzigdOp":"2022-12-23T10:10:38.1179878Z"},{"Id":"9da1820c-8c54-4656-b9f8-24f25f30d0c2","Soort":"Tegen","FractieGrootte":1,"ActorNaam":"Fractie Den Haan","ActorFractie":"Fractie Den Haan","GewijzigdOp":"2022-12-23T11:10:17.497+01:00","ApiGewijzigdOp":"2022-12-23T10:10:36.9461082Z"},{"Id":"7ec11f38-6f88-49f4-bee1-30d0fa8df218","Soort":"Voor","FractieGrootte":9,"ActorNaam":"PvdA","ActorFractie":"PvdA","GewijzigdOp":"2022-12-23T11:10:17.5+01:00","ApiGewijzigdOp":"2022-12-23T10:10:38.3367441Z"},{"Id":"da9928a0-8a56-4b3e-a586-45d6bd3c31d7","Soort":"Tegen","FractieGrootte":3,"ActorNaam":"DENK","ActorFractie":"DENK","GewijzigdOp":"2022-12-23T11:10:17.497+01:00","ApiGewijzigdOp":"2022-12-23T10:10:38.0711127Z"},{"Id":"aee523bd-9db1-4db5-aabc-4739403765de","Soort":"Voor","FractieGrootte":1,"ActorNaam":"BIJ1","ActorFractie":"BIJ1","GewijzigdOp":"2022-12-23T11:10:17.497+01:00","ApiGewijzigdOp":"2022-12-23T10:10:37.7898625Z"},{"Id":"64dab17c-f02c-4107-b99a-79ca6986f7fd","Soort":"Tegen","FractieGrootte":5,"ActorNaam":"ChristenUnie","ActorFractie":"ChristenUnie","GewijzigdOp":"2022-12-23T11:10:17.497+01:00","ApiGewijzigdOp":"2022-12-23T10:10:38.4930041Z"},{"Id":"89316e71-47e4-4905-9795-810185292bb0","Soort":"Voor","FractieGrootte":1,"ActorNaam":"BBB","ActorFractie":"BBB","GewijzigdOp":"2022-12-23T11:10:17.497+01:00","ApiGewijzigdOp":"2022-12-23T10:10:37.7742351Z"},{"Id":"52b1b101-fe4b-4013-a53d-853647cb0925","Soort":"Tegen","FractieGrootte":3,"ActorNaam":"Groep Van Haga","ActorFractie":"Groep Van Haga","GewijzigdOp":"2022-12-23T11:10:17.497+01:00","ApiGewijzigdOp":"2022-12-23T10:10:37.7429857Z"},{"Id":"2f41d041-9c6a-4ef9-9a4a-89b9a6861ed3","Soort":"Tegen","FractieGrootte":3,"ActorNaam":"JA21","ActorFractie":"JA21","GewijzigdOp":"2022-12-23T11:10:17.5+01:00","ApiGewijzigdOp":"2022-12-23T10:10:38.1961205Z"},{"Id":"27e0a0a6-70ff-4149-a8b7-961269a6445b","Soort":"Voor","FractieGrootte":8,"ActorNaam":"GroenLinks","ActorFractie":"GroenLinks","GewijzigdOp":"2022-12-23T11:10:17.497+01:00","ApiGewijzigdOp":"2022-12-23T10:10:38.274249Z"},{"Id":"312cf977-5434-4623-aac1-9c0b0afad5ce","Soort":"Tegen","FractieGrootte":1,"ActorNaam":"Omtzigt","ActorFractie":"Omtzigt","GewijzigdOp":"2022-12-23T11:10:17.5+01:00","ApiGewijzigdOp":"2022-12-23T10:10:38.0242433Z"},{"Id":"9db3f6d8-8497-4875-ac29-b0fba01c6414","Soort":"Tegen","FractieGrootte":14,"ActorNaam":"CDA","ActorFractie":"CDA","GewijzigdOp":"2022-12-23T11:10:17.497+01:00","ApiGewijzigdOp":"2022-12-23T10:10:37.8057403Z"},{"Id":"0e2f90d0-66ed-4958-af81-c1fac2c514de","Soort":"Niet deelgenomen","FractieGrootte":1,"ActorNaam":"Gündogan","ActorFractie":"Gündogan","GewijzigdOp":"2022-12-23T11:10:17.497+01:00","ApiGewijzigdOp":"2022-12-23T10:10:37.5086161Z"},{"Id":"18ce1f8d-ea8b-48c9-8dde-d8afe5fb293e","Soort":"Voor","FractieGrootte":9,"ActorNaam":"SP","ActorFractie":"SP","GewijzigdOp":"2022-12-23T11:10:17.5+01:00","ApiGewijzigdOp":"2022-12-23T10:10:38.211742Z"},{"Id":"17cfdee7-2641-47f2-a4b5-def413583989","Soort":"Tegen","FractieGrootte":3,"ActorNaam":"SGP","ActorFractie":"SGP","GewijzigdOp":"2022-12-23T11:10:17.5+01:00","ApiGewijzigdOp":"2022-12-23T10:10:38.4148673Z"},{"Id":"be496852-1fd3-4dca-87d1-f2a5d0270f21","Soort":"Tegen","FractieGrootte":17,"ActorNaam":"PVV","ActorFractie":"PVV","GewijzigdOp":"2022-12-23T11:10:17.5+01:00","ApiGewijzigdOp":"2022-12-23T10:10:38.1805006Z"},{"Id":"1c8b81e6-0e89-4b1f-9ff4-f3f26e3cbe61","Soort":"Tegen","FractieGrootte":5,"ActorNaam":"FVD","ActorFractie":"FVD","GewijzigdOp":"2022-12-23T11:10:17.497+01:00","ApiGewijzigdOp":"2022-12-23T10:10:38.102366Z"},{"Id":"1e19a0c0-74a6-4a3c-98ff-f82b82f47da5","Soort":"Voor","FractieGrootte":6,"ActorNaam":"PvdD","ActorFractie":"PvdD","GewijzigdOp":"2022-12-23T11:10:17.5+01:00","ApiGewijzigdOp":"2022-12-23T10:10:37.9929893Z"}],"Stats":{"Voor":36,"Tegen":113,"Anders":1,"PercentVoor":24,"PercentTegen":76}}]}