{"Id":"aff4999a-4923-4130-beb7-0ebefac352b2","Nummer":"2022Z04940","Titel":"Luchtvaartbeleid","Onderwerp":"Motie van het lid Koerhuis c.s. over onderzoeken hoe Groningen Airport Eelde economisch rendabel kan worden gemaakt ","GestartOp":"2022-03-15T00:00:00+01:00","Kabinetsappreciatie":"Oordeel Kamer","GewijzigdOp":"2022-03-22T15:58:25.637+01:00","ApiGewijzigdOp":"2023-01-25T12:45:01.6048727Z","ZaakActor":[{"Id":"b81cb9a7-ea55-4a33-970c-0106aecdfc7a","ActorNaam":"D.A.N. Koerhuis","ActorFractie":"VVD","GewijzigdOp":"2022-03-15T17:58:26.197+01:00","ApiGewijzigdOp":"2022-03-15T16:58:46.6067818Z"},{"Id":"852e3a33-d5d3-4d65-b08a-32bdb8254cbd","ActorNaam":"H. van der Molen","ActorFractie":"CDA","GewijzigdOp":"2022-03-15T17:58:26.197+01:00","ApiGewijzigdOp":"2022-03-15T16:58:46.5911568Z"},{"Id":"87eb611f-42d2-4437-91c2-7121e025f72c","ActorNaam":"D.J.G. Graus","ActorFractie":"PVV","GewijzigdOp":"2022-03-15T17:58:26.197+01:00","ApiGewijzigdOp":"2022-03-15T16:58:46.6224068Z"}],"Besluit":[{"Id":"ab79144d-2930-44b3-9cd3-57fce7107b09","StemmingsSoort":"Met handopsteken","BesluitSoort":"Stemmen - aangenomen","GewijzigdOp":"2022-03-22T15:58:20.613+01:00","ApiGewijzigdOp":"2022-03-22T14:58:43.9415697Z","Stemming":[{"Id":"68f4c1b7-f412-4cb2-acc8-0ca2c6b9aa0c","Soort":"Voor","FractieGrootte":1,"ActorNaam":"Omtzigt","ActorFractie":"Omtzigt","GewijzigdOp":"2022-03-23T09:45:12.453+01:00","ApiGewijzigdOp":"2022-03-23T08:46:03.5305453Z"},{"Id":"2bf703a2-bff5-46f6-bc26-2d4cce72b498","Soort":"Tegen","FractieGrootte":9,"ActorNaam":"SP","ActorFractie":"SP","GewijzigdOp":"2022-03-23T09:45:12.453+01:00","ApiGewijzigdOp":"2022-03-23T08:46:03.5461698Z"},{"Id":"73eb0ad2-4869-47a5-83bb-31a495c18b78","Soort":"Tegen","FractieGrootte":9,"ActorNaam":"PvdA","ActorFractie":"PvdA","GewijzigdOp":"2022-03-23T09:45:12.453+01:00","ApiGewijzigdOp":"2022-03-23T08:46:03.7336622Z"},{"Id":"d672f717-f95b-4a82-b610-554c277017cd","Soort":"Tegen","FractieGrootte":6,"ActorNaam":"PvdD","ActorFractie":"PvdD","GewijzigdOp":"2022-03-23T09:45:12.453+01:00","ApiGewijzigdOp":"2022-03-23T08:46:03.5617987Z"},{"Id":"cda2251d-66ab-40f9-854e-573d14792e57","Soort":"Voor","FractieGrootte":1,"ActorNaam":"Fractie Den Haan","ActorFractie":"Fractie Den Haan","GewijzigdOp":"2022-03-23T09:45:12.453+01:00","ApiGewijzigdOp":"2022-03-23T08:46:03.4055532Z"},{"Id":"4723d687-aac7-4bc4-8ecf-603749204a74","Soort":"Voor","FractieGrootte":3,"ActorNaam":"Groep Van Haga","ActorFractie":"Groep Van Haga","GewijzigdOp":"2022-03-23T09:45:12.453+01:00","ApiGewijzigdOp":"2022-03-23T08:46:03.7336622Z"},{"Id":"a0d44549-d4c8-4038-a78a-6f8da14d152b","Soort":"Tegen","FractieGrootte":8,"ActorNaam":"GroenLinks","ActorFractie":"GroenLinks","GewijzigdOp":"2022-03-23T09:45:12.453+01:00","ApiGewijzigdOp":"2022-03-23T08:46:03.4680475Z"},{"Id":"e2ea8cec-f24a-4054-b3f6-752ca5b8189d","Soort":"Tegen","FractieGrootte":2,"ActorNaam":"Volt","ActorFractie":"Volt","GewijzigdOp":"2022-03-23T09:45:12.453+01:00","ApiGewijzigdOp":"2022-03-23T08:46:03.4680475Z"},{"Id":"efc6fd92-19e9-4113-a213-7f74e40c5640","Soort":"Voor","FractieGrootte":24,"ActorNaam":"D66","ActorFractie":"D66","GewijzigdOp":"2022-03-23T09:45:12.453+01:00","ApiGewijzigdOp":"2022-03-23T08:46:03.7180434Z"},{"Id":"3704f53c-4704-4417-ae6b-95b0c8d52d0f","Soort":"Voor","FractieGrootte":3,"ActorNaam":"DENK","ActorFractie":"DENK","GewijzigdOp":"2022-03-23T09:45:12.453+01:00","ApiGewijzigdOp":"2022-03-23T08:46:03.452416Z"},{"Id":"ac20eb3d-9fcf-47bb-8f6f-97be75a349f9","Soort":"Voor","FractieGrootte":3,"ActorNaam":"SGP","ActorFractie":"SGP","GewijzigdOp":"2022-03-23T09:45:12.453+01:00","ApiGewijzigdOp":"2022-03-23T08:46:03.6555664Z"},{"Id":"2709480b-ae10-49e4-aa2a-97eab02d3c38","Soort":"Voor","FractieGrootte":34,"ActorNaam":"VVD","ActorFractie":"VVD","GewijzigdOp":"2022-03-23T09:45:12.453+01:00","ApiGewijzigdOp":"2022-03-23T08:46:03.6711733Z"},{"Id":"ec970b23-efa5-4368-b835-a2ecc7c259dc","Soort":"Voor","FractieGrootte":1,"ActorNaam":"BBB","ActorFractie":"BBB","GewijzigdOp":"2022-03-23T09:45:12.453+01:00","ApiGewijzigdOp":"2022-03-23T08:46:03.6867912Z"},{"Id":"3dc410e2-5abf-4343-a90d-a88befd02630","Soort":"Niet deelgenomen","FractieGrootte":1,"ActorNaam":"Gündogan","ActorFractie":"Gündogan","GewijzigdOp":"2022-03-23T09:45:12.453+01:00","ApiGewijzigdOp":"2022-03-23T08:46:03.4992973Z"},{"Id":"425b4abd-a183-4856-9a69-ac8ca279fccf","Soort":"Voor","FractieGrootte":5,"ActorNaam":"FVD","ActorFractie":"FVD","GewijzigdOp":"2022-03-23T09:45:12.453+01:00","ApiGewijzigdOp":"2022-03-23T08:46:03.4836785Z"},{"Id":"b34f91c0-ef65-46ae-9f2e-ba82471f9b10","Soort":"Voor","FractieGrootte":3,"ActorNaam":"JA21","ActorFractie":"JA21","GewijzigdOp":"2022-03-23T09:45:12.453+01:00","ApiGewijzigdOp":"2022-03-23T08:46:03.5930471Z"},{"Id":"20c0045e-77ef-4995-8684-c3ce6307b08c","Soort":"Voor","FractieGrootte":14,"ActorNaam":"CDA","ActorFractie":"CDA","GewijzigdOp":"2022-03-23T09:45:12.453+01:00","ApiGewijzigdOp":"2022-03-23T08:46:03.3899317Z"},{"Id":"c1665c50-9aeb-4cd8-ad03-d12da7bee58d","Soort":"Voor","FractieGrootte":17,"ActorNaam":"PVV","ActorFractie":"PVV","GewijzigdOp":"2022-03-23T09:45:12.453+01:00","ApiGewijzigdOp":"2022-03-23T08:46:03.6400095Z"},{"Id":"113ac9a7-4052-4cd3-9cc7-e07bd2bfc995","Soort":"Niet deelgenomen","FractieGrootte":1,"ActorNaam":"BIJ1","ActorFractie":"BIJ1","GewijzigdOp":"2022-03-23T09:45:12.453+01:00","ApiGewijzigdOp":"2022-03-23T08:46:03.7492978Z"},{"Id":"8803f6a6-55e4-458a-a376-f2e5d09c0927","Soort":"Voor","FractieGrootte":5,"ActorNaam":"ChristenUnie","ActorFractie":"ChristenUnie","GewijzigdOp":"2022-03-23T09:45:12.453+01:00","ApiGewijzigdOp":"2022-03-23T08:46:03.5149259Z"}],"Stats":{"Voor":114,"Tegen":34,"Anders":2,"PercentVoor":77,"PercentTegen":23}}]}