{"Id":"7b76f144-9972-4364-b623-9a62489dda1d","Nummer":"2022Z21708","Titel":"Nota over de toestand van ’s Rijks Financiën","Onderwerp":"Motie van het lid Van Haga over maatwerk leveren bij levensvatbare bedrijven door bijvoorbeeld voorschotten uit te keren ","GestartOp":"2022-11-10T00:00:00+01:00","Kabinetsappreciatie":"Ontraden","GewijzigdOp":"2022-11-15T16:16:28.807+01:00","ApiGewijzigdOp":"2022-11-16T14:00:39.601571Z","ZaakActor":[{"Id":"a334b389-2dbb-43d0-8ee2-8ce7963bcb4c","ActorNaam":"W.R. van Haga","ActorFractie":"Groep Van Haga","GewijzigdOp":"2022-11-10T20:06:10.417+01:00","ApiGewijzigdOp":"2022-11-10T19:07:24.4764371Z"}],"Besluit":[{"Id":"6190ca2e-d7e5-48d9-9434-819a29b0a7ec","StemmingsSoort":"Met handopsteken","BesluitSoort":"Stemmen - verworpen","GewijzigdOp":"2022-11-15T16:16:28.803+01:00","ApiGewijzigdOp":"2022-11-15T15:17:10.9909507Z","Stemming":[{"Id":"f4a8b40d-6078-4224-8377-0ea867361e10","Soort":"Niet deelgenomen","FractieGrootte":1,"ActorNaam":"Gündogan","ActorFractie":"Gündogan","GewijzigdOp":"2022-11-16T09:36:13.48+01:00","ApiGewijzigdOp":"2022-11-16T08:37:03.8576926Z"},{"Id":"7529c728-ff65-491b-a5cb-31681c43c15a","Soort":"Voor","FractieGrootte":9,"ActorNaam":"SP","ActorFractie":"SP","GewijzigdOp":"2022-11-16T09:36:13.48+01:00","ApiGewijzigdOp":"2022-11-16T08:37:04.2014627Z"},{"Id":"a7f18029-7b4e-46f8-96ce-3a1f572ca9b2","Soort":"Voor","FractieGrootte":3,"ActorNaam":"Groep Van Haga","ActorFractie":"Groep Van Haga","GewijzigdOp":"2022-11-16T09:36:13.48+01:00","ApiGewijzigdOp":"2022-11-16T08:37:04.3265436Z"},{"Id":"17424dd1-2f2f-4d48-b476-7662002e245b","Soort":"Tegen","FractieGrootte":34,"ActorNaam":"VVD","ActorFractie":"VVD","GewijzigdOp":"2022-11-16T09:36:13.48+01:00","ApiGewijzigdOp":"2022-11-16T08:37:04.4670941Z"},{"Id":"92237341-362a-4018-b243-77e36ca8377a","Soort":"Voor","FractieGrootte":8,"ActorNaam":"GroenLinks","ActorFractie":"GroenLinks","GewijzigdOp":"2022-11-16T09:36:13.48+01:00","ApiGewijzigdOp":"2022-11-16T08:37:04.3733531Z"},{"Id":"baf7410d-232e-4c1d-9d6e-84bd4d6ad518","Soort":"Tegen","FractieGrootte":5,"ActorNaam":"ChristenUnie","ActorFractie":"ChristenUnie","GewijzigdOp":"2022-11-16T09:36:13.48+01:00","ApiGewijzigdOp":"2022-11-16T08:37:03.8421154Z"},{"Id":"fcf97adf-2fb0-4a21-8599-887aea36bf98","Soort":"Voor","FractieGrootte":1,"ActorNaam":"Omtzigt","ActorFractie":"Omtzigt","GewijzigdOp":"2022-11-16T09:36:13.48+01:00","ApiGewijzigdOp":"2022-11-16T08:37:03.7326973Z"},{"Id":"73d5dfb9-28d4-4892-8a0b-8e9a445f736a","Soort":"Tegen","FractieGrootte":14,"ActorNaam":"CDA","ActorFractie":"CDA","GewijzigdOp":"2022-11-16T09:36:13.48+01:00","ApiGewijzigdOp":"2022-11-16T08:37:03.7795627Z"},{"Id":"aa322c6d-e419-4a79-a3b2-8f621f4e9405","Soort":"Voor","FractieGrootte":3,"ActorNaam":"SGP","ActorFractie":"SGP","GewijzigdOp":"2022-11-16T09:36:13.48+01:00","ApiGewijzigdOp":"2022-11-16T08:37:04.4827363Z"},{"Id":"9d4f86ef-428c-49a3-a661-91d9e889319d","Soort":"Voor","FractieGrootte":1,"ActorNaam":"BBB","ActorFractie":"BBB","GewijzigdOp":"2022-11-16T09:36:13.48+01:00","ApiGewijzigdOp":"2022-11-16T08:37:04.170215Z"},{"Id":"667a40f9-976a-499b-8c90-a1c207f9a589","Soort":"Voor","FractieGrootte":2,"ActorNaam":"Volt","ActorFractie":"Volt","GewijzigdOp":"2022-11-16T09:36:13.48+01:00","ApiGewijzigdOp":"2022-11-16T08:37:03.8264584Z"},{"Id":"e17d8c1e-336a-4aed-87fb-a1f460cb69c0","Soort":"Tegen","FractieGrootte":6,"ActorNaam":"PvdD","ActorFractie":"PvdD","GewijzigdOp":"2022-11-16T09:36:13.48+01:00","ApiGewijzigdOp":"2022-11-16T08:37:04.5139818Z"},{"Id":"393798d3-8b9d-4e38-aaec-ab00615b2387","Soort":"Voor","FractieGrootte":1,"ActorNaam":"BIJ1","ActorFractie":"BIJ1","GewijzigdOp":"2022-11-16T09:36:13.48+01:00","ApiGewijzigdOp":"2022-11-16T08:37:04.5139818Z"},{"Id":"dfcb5d41-4af9-4dfc-9d40-ad3e95103677","Soort":"Voor","FractieGrootte":3,"ActorNaam":"JA21","ActorFractie":"JA21","GewijzigdOp":"2022-11-16T09:36:13.48+01:00","ApiGewijzigdOp":"2022-11-16T08:37:04.4358411Z"},{"Id":"9baecf97-11ca-467e-b00c-b121f5732934","Soort":"Tegen","FractieGrootte":1,"ActorNaam":"Fractie Den Haan","ActorFractie":"Fractie Den Haan","GewijzigdOp":"2022-11-16T09:36:13.48+01:00","ApiGewijzigdOp":"2022-11-16T08:37:04.2483444Z"},{"Id":"b6c381c9-4fc9-4860-af2e-b53e539a01fa","Soort":"Voor","FractieGrootte":3,"ActorNaam":"DENK","ActorFractie":"DENK","GewijzigdOp":"2022-11-16T09:36:13.48+01:00","ApiGewijzigdOp":"2022-11-16T08:37:03.8108418Z"},{"Id":"c2c5b356-a53f-4383-9dbd-bff11f0ca778","Soort":"Voor","FractieGrootte":8,"ActorNaam":"PvdA","ActorFractie":"PvdA","GewijzigdOp":"2022-11-16T09:36:13.48+01:00","ApiGewijzigdOp":"2022-11-16T08:37:04.1389659Z"},{"Id":"e9dd193c-2e16-45af-9904-e878aece7f57","Soort":"Voor","FractieGrootte":5,"ActorNaam":"FVD","ActorFractie":"FVD","GewijzigdOp":"2022-11-16T09:36:13.48+01:00","ApiGewijzigdOp":"2022-11-16T08:37:04.3577116Z"},{"Id":"55ae9645-8c5f-4be2-ad69-eaf9cc51ce15","Soort":"Voor","FractieGrootte":17,"ActorNaam":"PVV","ActorFractie":"PVV","GewijzigdOp":"2022-11-16T09:36:13.48+01:00","ApiGewijzigdOp":"2022-11-16T08:37:03.9514537Z"},{"Id":"42a34c82-f74f-46da-b3dc-ec71d665562c","Soort":"Tegen","FractieGrootte":24,"ActorNaam":"D66","ActorFractie":"D66","GewijzigdOp":"2022-11-16T09:36:13.48+01:00","ApiGewijzigdOp":"2022-11-16T08:37:03.7171054Z"}],"Stats":{"Voor":64,"Tegen":84,"Anders":1,"PercentVoor":43,"PercentTegen":57}}]}