{"Id":"6c6bc6d7-f119-407b-8d5f-5ed83f386cd6","Nummer":"2022Z11606","Titel":"Luchtvaartbeleid","Onderwerp":"Motie van het lid Kröger c.s. over de dienstbaarheid van Schiphol aan Nederland centraal stellen","GestartOp":"2022-06-09T00:00:00+02:00","Kabinetsappreciatie":"Oordeel Kamer","GewijzigdOp":"2022-06-14T16:06:45.363+02:00","ApiGewijzigdOp":"2022-07-05T12:07:06.6836977Z","ZaakActor":[{"Id":"9d629877-330d-4cb3-af5f-1a350633861c","ActorNaam":"H.E. de Hoop","ActorFractie":"PvdA","GewijzigdOp":"2022-06-09T10:28:18.98+02:00","ApiGewijzigdOp":"2022-06-09T08:29:00.8971088Z"},{"Id":"e7920ed7-6fe8-4ce0-aacb-a7f6094fb922","ActorNaam":"S.C. Kröger","ActorFractie":"GroenLinks","GewijzigdOp":"2022-06-09T10:28:18.98+02:00","ApiGewijzigdOp":"2022-06-09T08:29:00.6627304Z"},{"Id":"bcde5f6b-81a8-4fe3-b788-ab1f0f5fdefa","ActorNaam":"M.Ö. Alkaya","ActorFractie":"SP","GewijzigdOp":"2022-06-09T10:28:18.98+02:00","ApiGewijzigdOp":"2022-06-09T08:29:00.9283645Z"},{"Id":"1bd9b6f2-94f7-4df7-90a3-c069c9c4e22a","ActorNaam":"L. van Raan","ActorFractie":"PvdD","GewijzigdOp":"2022-06-09T10:28:18.98+02:00","ApiGewijzigdOp":"2022-06-09T08:29:00.9127449Z"}],"Besluit":[{"Id":"12e66b03-6952-4357-8c03-ed405839b615","StemmingsSoort":"Met handopsteken","BesluitSoort":"Stemmen - aangenomen","GewijzigdOp":"2022-06-14T16:06:45.35+02:00","ApiGewijzigdOp":"2022-06-14T14:08:05.0170589Z","Stemming":[{"Id":"038511d3-4717-4540-84c4-03aca1d951cb","Soort":"Voor","FractieGrootte":24,"ActorNaam":"D66","ActorFractie":"D66","GewijzigdOp":"2022-06-15T11:26:51.597+02:00","ApiGewijzigdOp":"2022-06-15T09:27:56.405301Z"},{"Id":"29db4592-1713-4e8b-8a53-1b60d16f6178","Soort":"Voor","FractieGrootte":3,"ActorNaam":"DENK","ActorFractie":"DENK","GewijzigdOp":"2022-06-15T11:26:51.597+02:00","ApiGewijzigdOp":"2022-06-15T09:27:56.4365494Z"},{"Id":"3c16db26-fbf4-4c98-8947-1c26d79a61fb","Soort":"Voor","FractieGrootte":9,"ActorNaam":"PvdA","ActorFractie":"PvdA","GewijzigdOp":"2022-06-15T11:26:51.613+02:00","ApiGewijzigdOp":"2022-06-15T09:27:56.8115428Z"},{"Id":"24f54f2c-71d6-4892-b987-2629c2f58882","Soort":"Voor","FractieGrootte":14,"ActorNaam":"CDA","ActorFractie":"CDA","GewijzigdOp":"2022-06-15T11:26:51.597+02:00","ApiGewijzigdOp":"2022-06-15T09:27:56.4521901Z"},{"Id":"eafb08f9-c063-4a4c-8e12-3804a3d150e1","Soort":"Niet deelgenomen","FractieGrootte":1,"ActorNaam":"BIJ1","ActorFractie":"BIJ1","GewijzigdOp":"2022-06-15T11:26:51.597+02:00","ApiGewijzigdOp":"2022-06-15T09:27:56.795925Z"},{"Id":"583a92ec-be93-42c5-a5b0-5644846aef9c","Soort":"Voor","FractieGrootte":6,"ActorNaam":"PvdD","ActorFractie":"PvdD","GewijzigdOp":"2022-06-15T11:26:51.613+02:00","ApiGewijzigdOp":"2022-06-15T09:27:56.6709096Z"},{"Id":"45868761-0568-4c31-8bc1-59292ae98386","Soort":"Voor","FractieGrootte":2,"ActorNaam":"Volt","ActorFractie":"Volt","GewijzigdOp":"2022-06-15T11:26:51.613+02:00","ApiGewijzigdOp":"2022-06-15T09:27:56.2490542Z"},{"Id":"c6155495-6e6a-4793-99c6-5d9db0f2a742","Soort":"Tegen","FractieGrootte":17,"ActorNaam":"PVV","ActorFractie":"PVV","GewijzigdOp":"2022-06-15T11:26:51.613+02:00","ApiGewijzigdOp":"2022-06-15T09:27:56.8584182Z"},{"Id":"6d6dc077-d708-4264-9e93-6e29b7d1938e","Soort":"Voor","FractieGrootte":8,"ActorNaam":"GroenLinks","ActorFractie":"GroenLinks","GewijzigdOp":"2022-06-15T11:26:51.597+02:00","ApiGewijzigdOp":"2022-06-15T09:27:56.3115508Z"},{"Id":"899882ed-7b78-47fd-90d6-8852afa98342","Soort":"Tegen","FractieGrootte":5,"ActorNaam":"FVD","ActorFractie":"FVD","GewijzigdOp":"2022-06-15T11:26:51.597+02:00","ApiGewijzigdOp":"2022-06-15T09:27:56.2334079Z"},{"Id":"cf23b826-5293-407b-a98e-9212f21fb5a1","Soort":"Voor","FractieGrootte":1,"ActorNaam":"Omtzigt","ActorFractie":"Omtzigt","GewijzigdOp":"2022-06-15T11:26:51.613+02:00","ApiGewijzigdOp":"2022-06-15T09:27:56.3896632Z"},{"Id":"cfb82082-6893-416a-91e2-9b7910cc75a3","Soort":"Voor","FractieGrootte":9,"ActorNaam":"SP","ActorFractie":"SP","GewijzigdOp":"2022-06-15T11:26:51.613+02:00","ApiGewijzigdOp":"2022-06-15T09:27:56.2959111Z"},{"Id":"2658caf2-b2d4-40d9-b68a-a35d54684101","Soort":"Voor","FractieGrootte":1,"ActorNaam":"BBB","ActorFractie":"BBB","GewijzigdOp":"2022-06-15T11:26:51.597+02:00","ApiGewijzigdOp":"2022-06-15T09:27:56.3740337Z"},{"Id":"5dad24a1-c1b4-40f9-9d10-a7dc107fa30f","Soort":"Tegen","FractieGrootte":34,"ActorNaam":"VVD","ActorFractie":"VVD","GewijzigdOp":"2022-06-15T11:26:51.613+02:00","ApiGewijzigdOp":"2022-06-15T09:27:56.8740303Z"},{"Id":"5aecde40-cb97-4834-897b-b48db84513b2","Soort":"Voor","FractieGrootte":5,"ActorNaam":"ChristenUnie","ActorFractie":"ChristenUnie","GewijzigdOp":"2022-06-15T11:26:51.597+02:00","ApiGewijzigdOp":"2022-06-15T09:27:56.4834127Z"},{"Id":"e23af5c4-1184-41e9-ae2f-c12bde9e4bc8","Soort":"Tegen","FractieGrootte":3,"ActorNaam":"JA21","ActorFractie":"JA21","GewijzigdOp":"2022-06-15T11:26:51.613+02:00","ApiGewijzigdOp":"2022-06-15T09:27:56.7021646Z"},{"Id":"d47c1f36-94d4-4e82-b81b-c87b97cea2d2","Soort":"Voor","FractieGrootte":3,"ActorNaam":"SGP","ActorFractie":"SGP","GewijzigdOp":"2022-06-15T11:26:51.613+02:00","ApiGewijzigdOp":"2022-06-15T09:27:56.8271611Z"},{"Id":"694da46c-4b73-47a1-b70f-cac1681afa2a","Soort":"Voor","FractieGrootte":1,"ActorNaam":"Gündogan","ActorFractie":"Gündogan","GewijzigdOp":"2022-06-15T11:26:51.613+02:00","ApiGewijzigdOp":"2022-06-15T09:27:56.2959111Z"},{"Id":"52c61eb6-40a5-4eb3-b267-cdd4d7737d60","Soort":"Voor","FractieGrootte":3,"ActorNaam":"Groep Van Haga","ActorFractie":"Groep Van Haga","GewijzigdOp":"2022-06-15T11:26:51.613+02:00","ApiGewijzigdOp":"2022-06-15T09:27:56.3427945Z"},{"Id":"81dc9486-3020-4b76-aaf9-dacb5be1802c","Soort":"Voor","FractieGrootte":1,"ActorNaam":"Fractie Den Haan","ActorFractie":"Fractie Den Haan","GewijzigdOp":"2022-06-15T11:26:51.597+02:00","ApiGewijzigdOp":"2022-06-15T09:27:56.7334063Z"}],"Stats":{"Voor":90,"Tegen":59,"Anders":1,"PercentVoor":60,"PercentTegen":40}}]}