{"Id":"704cda92-8813-470c-a8b5-fe0b08fb5077","Nummer":"2022Z23874","Titel":"Vaststelling van de begrotingsstaten van het Ministerie van Infrastructuur en Waterstaat (XII) voor het jaar 2023","Onderwerp":"Motie van het lid Hagen c.s. over een voorstel voor een circulaire-economiewet ","GestartOp":"2022-12-01T00:00:00+01:00","Kabinetsappreciatie":"Oordeel Kamer","GewijzigdOp":"2022-12-06T16:41:21.933+01:00","ApiGewijzigdOp":"2022-12-06T15:41:59.8688378Z","ZaakActor":[{"Id":"96559419-0aa2-4fe6-9f3e-089229af2120","ActorNaam":"R.M. Boucke","ActorFractie":"D66","GewijzigdOp":"2022-12-01T23:00:57.32+01:00","ApiGewijzigdOp":"2022-12-01T22:01:57.1202281Z"},{"Id":"341287e1-b197-4c8c-9848-1e27a97e7e05","ActorNaam":"K.B. Hagen","ActorFractie":"D66","GewijzigdOp":"2022-12-01T23:00:57.32+01:00","ApiGewijzigdOp":"2022-12-01T22:01:57.1514908Z"},{"Id":"d0daa075-e1c3-4009-8e0c-b68f480e0808","ActorNaam":"A.H. (Agnes) Mulder","ActorFractie":"CDA","GewijzigdOp":"2022-12-01T23:00:57.32+01:00","ApiGewijzigdOp":"2022-12-01T22:01:57.10462Z"},{"Id":"e1e6a13f-3bb5-4e3e-8ed6-d0d6de757377","ActorNaam":"S.J.F. van der Graaf","ActorFractie":"ChristenUnie","GewijzigdOp":"2022-12-01T23:00:57.32+01:00","ApiGewijzigdOp":"2022-12-01T22:01:57.1358511Z"},{"Id":"0866f2dc-9c21-4071-87e2-d95e919a287a","ActorNaam":"E.M. van Esch","ActorFractie":"PvdD","GewijzigdOp":"2022-12-01T23:00:57.32+01:00","ApiGewijzigdOp":"2022-12-01T22:01:57.1983588Z"}],"Besluit":[{"Id":"66b27682-b6a9-4e45-82ec-748d5e97235c","StemmingsSoort":"Met handopsteken","BesluitSoort":"Stemmen - aangenomen","GewijzigdOp":"2022-12-06T16:41:21.9+01:00","ApiGewijzigdOp":"2022-12-06T15:41:49.728032Z","Stemming":[{"Id":"0346081c-0f88-464c-b88a-10ee5d06373a","Soort":"Voor","FractieGrootte":9,"ActorNaam":"PvdA","ActorFractie":"PvdA","GewijzigdOp":"2022-12-07T12:26:15.41+01:00","ApiGewijzigdOp":"2022-12-07T11:26:51.222732Z"},{"Id":"1e9c63ae-d712-41be-b6b0-11e96be6f674","Soort":"Tegen","FractieGrootte":3,"ActorNaam":"JA21","ActorFractie":"JA21","GewijzigdOp":"2022-12-07T12:26:15.407+01:00","ApiGewijzigdOp":"2022-12-07T11:26:51.4571363Z"},{"Id":"8080b6d6-b726-4cea-82d5-213f2d9ebe34","Soort":"Voor","FractieGrootte":1,"ActorNaam":"Fractie Den Haan","ActorFractie":"Fractie Den Haan","GewijzigdOp":"2022-12-07T12:26:15.407+01:00","ApiGewijzigdOp":"2022-12-07T11:26:51.379448Z"},{"Id":"d0d6f20f-61c9-49fa-862a-25c31490cf71","Soort":"Voor","FractieGrootte":34,"ActorNaam":"VVD","ActorFractie":"VVD","GewijzigdOp":"2022-12-07T12:26:15.41+01:00","ApiGewijzigdOp":"2022-12-07T11:26:51.3008624Z"},{"Id":"43089629-aadb-4f9d-8364-322313d23d98","Soort":"Tegen","FractieGrootte":3,"ActorNaam":"Groep Van Haga","ActorFractie":"Groep Van Haga","GewijzigdOp":"2022-12-07T12:26:15.407+01:00","ApiGewijzigdOp":"2022-12-07T11:26:51.4102428Z"},{"Id":"65aad982-0c09-4bf0-b914-520e5d4dbac0","Soort":"Voor","FractieGrootte":2,"ActorNaam":"Volt","ActorFractie":"Volt","GewijzigdOp":"2022-12-07T12:26:15.41+01:00","ApiGewijzigdOp":"2022-12-07T11:26:51.2852458Z"},{"Id":"381acd6f-d9b1-4295-a59b-53b4998275a4","Soort":"Tegen","FractieGrootte":17,"ActorNaam":"PVV","ActorFractie":"PVV","GewijzigdOp":"2022-12-07T12:26:15.41+01:00","ApiGewijzigdOp":"2022-12-07T11:26:51.3946149Z"},{"Id":"8d649777-c59a-4947-a2a2-69e67e41e326","Soort":"Voor","FractieGrootte":3,"ActorNaam":"SGP","ActorFractie":"SGP","GewijzigdOp":"2022-12-07T12:26:15.41+01:00","ApiGewijzigdOp":"2022-12-07T11:26:51.4571363Z"},{"Id":"71f82e7a-3ea6-4589-ae83-6b17fa605f13","Soort":"Voor","FractieGrootte":1,"ActorNaam":"Gündogan","ActorFractie":"Gündogan","GewijzigdOp":"2022-12-07T12:26:15.407+01:00","ApiGewijzigdOp":"2022-12-07T11:26:51.2383709Z"},{"Id":"c4599f1f-e73c-45c5-a603-8dcb45036778","Soort":"Voor","FractieGrootte":5,"ActorNaam":"ChristenUnie","ActorFractie":"ChristenUnie","GewijzigdOp":"2022-12-07T12:26:15.407+01:00","ApiGewijzigdOp":"2022-12-07T11:26:51.2071226Z"},{"Id":"feef50b7-4976-41b4-9ff4-9096754fd45f","Soort":"Voor","FractieGrootte":3,"ActorNaam":"DENK","ActorFractie":"DENK","GewijzigdOp":"2022-12-07T12:26:15.407+01:00","ApiGewijzigdOp":"2022-12-07T11:26:51.3321118Z"},{"Id":"664b5c4f-ad7d-423c-82b6-a18463d69450","Soort":"Voor","FractieGrootte":24,"ActorNaam":"D66","ActorFractie":"D66","GewijzigdOp":"2022-12-07T12:26:15.407+01:00","ApiGewijzigdOp":"2022-12-07T11:26:51.1914867Z"},{"Id":"ff6810f0-c0a2-4bcc-8f78-ab22d8e79d5e","Soort":"Voor","FractieGrootte":1,"ActorNaam":"BIJ1","ActorFractie":"BIJ1","GewijzigdOp":"2022-12-07T12:26:15.407+01:00","ApiGewijzigdOp":"2022-12-07T11:26:51.4414868Z"},{"Id":"afdc05c3-b8eb-474d-a46d-b0c363d78899","Soort":"Voor","FractieGrootte":6,"ActorNaam":"PvdD","ActorFractie":"PvdD","GewijzigdOp":"2022-12-07T12:26:15.41+01:00","ApiGewijzigdOp":"2022-12-07T11:26:51.5196158Z"},{"Id":"6b3cd6e1-d91f-4cdd-9615-b9ed568ebbb6","Soort":"Voor","FractieGrootte":14,"ActorNaam":"CDA","ActorFractie":"CDA","GewijzigdOp":"2022-12-07T12:26:15.407+01:00","ApiGewijzigdOp":"2022-12-07T11:26:51.3633628Z"},{"Id":"a5413cd8-3263-45b0-8d0c-bb6fd73cb461","Soort":"Voor","FractieGrootte":1,"ActorNaam":"Omtzigt","ActorFractie":"Omtzigt","GewijzigdOp":"2022-12-07T12:26:15.41+01:00","ApiGewijzigdOp":"2022-12-07T11:26:51.2696253Z"},{"Id":"ef27f703-d31c-4cc7-aab8-c35dac3caab5","Soort":"Voor","FractieGrootte":9,"ActorNaam":"SP","ActorFractie":"SP","GewijzigdOp":"2022-12-07T12:26:15.41+01:00","ApiGewijzigdOp":"2022-12-07T11:26:51.5039926Z"},{"Id":"5a76d2a4-f99d-40c7-95fd-c6d38d6dd3e0","Soort":"Tegen","FractieGrootte":1,"ActorNaam":"BBB","ActorFractie":"BBB","GewijzigdOp":"2022-12-07T12:26:15.407+01:00","ApiGewijzigdOp":"2022-12-07T11:26:51.4258797Z"},{"Id":"aaa57431-b817-4756-9765-c8c0527df1db","Soort":"Voor","FractieGrootte":8,"ActorNaam":"GroenLinks","ActorFractie":"GroenLinks","GewijzigdOp":"2022-12-07T12:26:15.407+01:00","ApiGewijzigdOp":"2022-12-07T11:26:51.2539847Z"},{"Id":"b9ae1deb-bab7-46ad-915a-d3ee01d202c0","Soort":"Tegen","FractieGrootte":5,"ActorNaam":"FVD","ActorFractie":"FVD","GewijzigdOp":"2022-12-07T12:26:15.407+01:00","ApiGewijzigdOp":"2022-12-07T11:26:51.4883852Z"}],"Stats":{"Voor":121,"Tegen":29,"Anders":0,"PercentVoor":80,"PercentTegen":20}}]}